onetokenpy/__init__.py
onetokenpy/attachments_handlers.py
onetokenpy/core.py
onetokenpy/helpers.py
onetokenpy-0.2.0.dist-info/licenses/LICENSE
onetokenpy-0.2.0.dist-info/METADATA
onetokenpy-0.2.0.dist-info/WHEEL
onetokenpy-0.2.0.dist-info/top_level.txt
onetokenpy-0.2.0.dist-info/RECORD
