Metadata-Version: 2.4
Name: onetokenpy
Version: 0.2.0
Summary: High-level utilities for seamless LLM interaction, context, and tool use.
Author-email: Maxime Rivest <mrive052@gmail.com>
License:                                  Apache License
Project-URL: Homepage, https://github.com/maximerivest/onetokenpy
Project-URL: Bug Tracker, https://github.com/maximerivest/onetokenpy/issues
Classifier: Development Status :: 3 - Alpha
Classifier: Intended Audience :: Developers
Classifier: License :: OSI Approved :: Apache Software License
Classifier: Programming Language :: Python :: 3
Classifier: Programming Language :: Python :: 3.8
Classifier: Programming Language :: Python :: 3.9
Classifier: Programming Language :: Python :: 3.10
Classifier: Programming Language :: Python :: 3.11
Classifier: Programming Language :: Python :: 3.12
Classifier: Operating System :: OS Independent
Classifier: Topic :: Software Development :: Libraries :: Python Modules
Classifier: Topic :: Scientific/Engineering :: Artificial Intelligence
Requires-Python: >=3.8
License-File: LICENSE
Requires-Dist: claudette
Requires-Dist: openai
Requires-Dist: anthropic
Requires-Dist: cosette
Requires-Dist: requests
Requires-Dist: pymupdf
Requires-Dist: python-pptx
Requires-Dist: pandas
Requires-Dist: pillow-heif
Requires-Dist: PyYAML
Provides-Extra: extras
Dynamic: license-file
